e2efs/.DS_Store
e2efs/__init__.py
e2efs/callbacks.py
e2efs/e2efs_layers.py
e2efs/e2efs_layers_tf2.py
e2efs/models.py
e2efs/optimizers.py
e2efs/optimizers_tf2.py
e2efs/optimizers_tf29.py
e2efs-0.0.3.dist-info/METADATA
e2efs-0.0.3.dist-info/WHEEL
e2efs-0.0.3.dist-info/licenses/LICENSE
e2efs-0.0.3.dist-info/RECORD
