Metadata-Version: 2.1
Name: e2efs
Version: 0.0.3
Summary: E2E-FS Feature Selection Method
Project-URL: Homepage, https://github.com/braisCB/E2E-FS
Project-URL: Bug Tracker, https://github.com/braisCB/E2E-FS/issues
Author-email: Brais Cancela <brais.cancela@udc.es>
License: GNU GENERAL PUBLIC LICENSE
License-File: LICENSE
Classifier: Development Status :: 4 - Beta
Classifier: License :: OSI Approved :: GNU General Public License v3 or later (GPLv3+)
Classifier: Programming Language :: Python :: 3 :: Only
Classifier: Programming Language :: Python :: 3.7
Classifier: Programming Language :: Python :: 3.8
Classifier: Programming Language :: Python :: 3.9
Classifier: Programming Language :: Python :: 3.10
Classifier: Programming Language :: Python :: 3.11
Classifier: Topic :: Scientific/Engineering :: Physics
Requires-Python: >=3.7
Requires-Dist: packaging
Requires-Dist: tensorflow-macos; sys_platform == 'darwin' and platform_machine == 'arm64'
Requires-Dist: tensorflow; sys_platform != 'darwin' or platform_machine != 'arm64'
